lidia/__init__.py
lidia/__main__.py
lidia/aircraft.py
lidia/config.py
lidia/lidia.py
lidia/mavlink_all.py
lidia/mytypes.py
lidia/server.py
lidia/pages/approach.html
lidia/pages/cas.html
lidia/pages/controls.html
lidia/pages/info.html
lidia/pages/pfd.html
lidia/pages/static/LICENSE.txt
lidia/pages/static/RobotoMono-Bold.ttf
lidia/pages/static/RobotoMono-ExtraLight.ttf
lidia/pages/static/RobotoMono-Light.ttf
lidia/pages/static/RobotoMono-Medium.ttf
lidia/pages/static/RobotoMono-Regular.ttf
lidia/pages/static/RobotoMono-SemiBold.ttf
lidia/pages/static/RobotoMono-Thin.ttf
lidia/pages/static/controls.js
lidia/pages/static/socket.io.js
lidia/pages/static/style.css
lidia/sources/__init__.py
lidia/sources/approach.py
lidia/sources/confighelp.md
lidia/sources/confighelp.py
lidia/sources/demo.py
lidia/sources/flightgear.py
lidia/sources/marsh.py
lidia/sources/mytypes.py
lidia/sources/rpctask.py
lidia/sources/smol.py
lidia/utils/pack_lidia.m
lidia/utils/pack_maker.py
lidia/utils/update_mavlink.py
lidia-0.14.0.dist-info/licenses/LICENSE.txt
lidia-0.14.0.dist-info/METADATA
lidia-0.14.0.dist-info/WHEEL
lidia-0.14.0.dist-info/entry_points.txt
lidia-0.14.0.dist-info/top_level.txt
lidia-0.14.0.dist-info/RECORD
