Metadata-Version: 2.4
Name: lidia
Version: 0.14.0
Summary: serve an aircraft instruments panel as a web page
Home-page: https://codeberg.org/Maarrk/lidia
Author: Marek S. Lukasiewicz
Author-email: marek@lukasiewicz.tech
Classifier: Programming Language :: Python :: 3
Classifier: License :: OSI Approved :: MIT License
Classifier: Operating System :: OS Independent
Requires-Python: >=3.7
License-File: LICENSE.txt
Requires-Dist: eventlet~=0.36
Requires-Dist: msgpack~=1.0
Requires-Dist: pydantic~=1.10
Requires-Dist: pymavlink~=2.4
Requires-Dist: python-socketio~=5.6
Requires-Dist: PyYAML~=6.0
Requires-Dist: tomli~=2.0
Dynamic: license-file
